llm_caching/__init__.py
llm_caching/agent.py
llm_caching/config.py
llm_caching/costs.py
llm_caching/exceptions.py
llm_caching/types.py
pydanticai_llm_caching-0.1.0.dist-info/LICENSE
pydanticai_llm_caching-0.1.0.dist-info/METADATA
pydanticai_llm_caching-0.1.0.dist-info/WHEEL
pydanticai_llm_caching-0.1.0.dist-info/RECORD
