Metadata-Version: 2.3
Name: pydanticAI-llm-caching
Version: 0.1.0
Summary: Redis-based caching for Pydantic AI LLM agents with cost tracking
License: MIT
Keywords: llm,caching,redis,ai,cost-tracking
Author: Andrew de Jonge
Author-email: talkingtoaj@hotmail.com
Requires-Python: >=3.9,<4.0
Classifier: Development Status :: 4 - Beta
Classifier: Intended Audience :: Developers
Classifier: License :: OSI Approved :: MIT License
Classifier: Programming Language :: Python :: 3
Classifier: Programming Language :: Python :: 3.9
Classifier: Programming Language :: Python :: 3.10
Classifier: Programming Language :: Python :: 3.11
Classifier: Programming Language :: Python :: 3.12
Classifier: Programming Language :: Python :: 3.13
Classifier: Topic :: Software Development :: Libraries :: Python Modules
Requires-Dist: pydantic (>=2.6.1,<3.0.0)
Requires-Dist: pydantic-ai (>=0.1.0,<0.2.0)
Requires-Dist: redis (>=5.0.1,<6.0.0)
Requires-Dist: typing-extensions (>=4.9.0,<5.0.0)
